sticky_marshmallow/__init__.py
sticky_marshmallow/connection.py
sticky_marshmallow/core.py
sticky_marshmallow/cursor.py
sticky_marshmallow/repository.py
sticky_marshmallow/utils/case.py
sticky_marshmallow-0.1.2.dist-info/LICENSE
sticky_marshmallow-0.1.2.dist-info/METADATA
sticky_marshmallow-0.1.2.dist-info/WHEEL
sticky_marshmallow-0.1.2.dist-info/top_level.txt
sticky_marshmallow-0.1.2.dist-info/RECORD
